{
  "id": "f72eaa11-89f4-32b4-3a68-334e0f75af52",
  "details": "Lorem ipsum dolor sit amet, usu et omnesque facilisi, ut conceptam constituam eos. Eum quod mazim iudicabit in, iudico lucilius honestatis per at. Prima tamquam eruditi ius at, possim albucius at vix. Vix ei petentium consequat, qui ex viderer atomorum. Mentitum abhorreant est ei.",
  "img": "https://pisces.bbystatic.com/image2/BestBuy_US/images/products/5621/5621780_sa.jpg;maxHeight=145;maxWidth=222",
  "model": "CP.PT.000500",
  "price": "999.99",
  "sku": "5621780",
  "title": "DJI - Mavic Pro Quadcopter with Remote Controller - Gray"
}